Workbook

Sheet DCF>

Sheet WACC
B5: Weighted average cost of capital
B7: all figures are in INR unless stated otherwise
B10: Peer comps
G11: debt/ | H11: debt/ | I11: Levered | J11: Unlevered
B12: Name of the comp | C12: country | D12: total debt | E12: total equity | F12: Taxrate 1 | G12: equity | H12: capital | I12: Beta 2 | J12: Beta 3
B14: Avenue Super. | C14: India | D14: ='COMPS BETA'!F5 -> 1609.19 | E14: ='COMPS BETA'!E5 -> 252211.12 | F14: 0.3 | G14: =D14/E14 -> 0.0063803293 | H14: =D14/(D14+E14) -> 0.0063398788 | I14: ='REGRESSION BETA'!J6 -> 0.0052044999 | J14: =I14/(1+(1-F14)*G14) -> 0.0051813587
B15: Eternal | C15: India | D15: ='COMPS BETA'!F6 -> 3351 | E15: ='COMPS BETA'!E6 -> 224438.21 | F15: 0.3 | G15: =D15/E15 -> 0.014930613 | H15: =D15/(D15+E15) -> 0.014710969 | I15: 0.135 | J15: =I15/(1+(1-F15)*G15) -> 0.13360365
B16: Trent | C16: India | D16: ='COMPS BETA'!F7 -> 2348.57 | E16: ='COMPS BETA'!E7 -> 132340.87 | F16: 0.3 | G16: =D16/E16 -> 0.01774637 | H16: =D16/(D16+E16) -> 0.017436927 | I16: 0.166 | J16: =I16/(1+(1-F16)*G16) -> 0.16396317
B17: Lenskart Solut. | C17: India | D17: ='COMPS BETA'!F8 -> 2857.8 | E17: ='COMPS BETA'!E8 -> 90311 | F17: 0.3 | G17: =D17/E17 -> 0.031643986 | H17: =D17/(D17+E17) -> 0.030673358 | I17: 0.01 | J17: =I17/(1+(1-F17)*G17) -> 0.0097832923
B18: Swiggy | C18: India | D18: ='COMPS BETA'!F9 -> 2491 | E18: ='COMPS BETA'!E9 -> 83223.45 | F18: 0.3 | G18: =D18/E18 -> 0.029931468 | H18: =D18/(D18+E18) -> 0.029061611 | I18: 0.02 | J18: =I18/(1+(1-F18)*G18) -> 0.019589559
E20: Average | F20: =AVERAGE(F14:F18) -> 0.3 | G20: =AVERAGE(G14:G18) -> 0.020126553 | H20: =AVERAGE(H14:H18) -> 0.019644549 | I20: =AVERAGE(I14:I18) -> 0.0672409 | J20: =AVERAGE(J14:J18) -> 0.066424207
E21: Median | F21: =MEDIAN(F14:F18) -> 0.3 | G21: =MEDIAN(G14:G18) -> 0.01774637 | H21: =MEDIAN(H14:H18) -> 0.017436927 | I21: =MEDIAN(I14:I18) -> 0.02 | J21: =MEDIAN(J14:J18) -> 0.019589559
B24: Cost of debt | F24: Cost Of Equity
B26: Pre Tax Cost of debt | D26: =69/D14 -> 0.042878715 | F26: Risk Free Rate | J26: 0.06688
B27: Tax rate | D27: =J36 -> 0.3 | F27: Equity Risk Premium | J27: ='Rm '!F7-WACC!J26 -> 0.086468
B28: Post tax cost of debt | D28: =D26*(1-D27) -> 0.030015101 | F28: Levered Beta 4 | J28: =J37 -> 0.025348665
F29: Cost of Equity | J29: =J26+J27*J28 -> 0.069071848
B32: Capital Structure | F32: Levered Beta
D34: Current | E34: Target | F34: Comp Median Unlevered Beta | J34: 0.019589559
B35: Total Debt | C35: =D14 -> 1609.19 | D35: =C35/$C$37 -> 0.0063398788 | E35: =H20 -> 0.019644549 | F35: Target debt/equity | J35: =E41 -> 0.02003819
B36: Market capitiliziation | C36: =E14 -> 252211.12 | D36: =C36/$C$37 -> 0.99366012 | E36: =E37-E35 -> 0.98035545 | F36: Tax rate | J36: =F14 -> 0.3
B37: Total capitaliziation | C37: =SUM(C35:C36) -> 253820.31 | D37: =C37/$C$37 -> 1 | E37: 1 | F37: Levered Beta | J37: =J34*(1+(1-J35)*J36) -> 0.025348665
F40: Weighted Average Cost of Capital
B41: Debt/Equity | D41: =D35/D36 -> 0.0063803293 | E41: =E35/E36 -> 0.02003819
F42: Cost of Equity | J42: =J29 -> 0.069071848
F43: Equity Weight | J43: =E36 -> 0.98035545
F45: Cost of Debt | J45: =D28 -> 0.030015101
F46: Debt Weight | J46: =E35 -> 0.019644549
F48: WACC | J48: =(J42*J43)+(J45*J46) -> 0.068304596

Sheet DATA>

Sheet REGRESSION BETA
B2: Regression Beta
B4: Avenue Supermart Weekly Returns | F4: NIFTY Returns | I4: Beta Drifting
B6: Date | C6: Closing Price | D6: Returns | F6: Closing Price | G6: Returns | I6: Levered Raw Beta | J6: =S9 -> 0.0052044999
B7: Feb 27, 2026 | C7: 3897.6 | F7: 14529.15 | I7: Beta Weight | J7: 0.75
B8: Feb 1, 2026 | C8: 3847.6 | D8: =C8/C7-1 -> -0.012828407 | F8: 14938.1 | G8: =F8/F7-1 -> 0.028146863
B9: Jan 1, 2026 | C9: 3689.5 | D9: =C9/C8-1 -> -0.04109055 | F9: 15030.95 | G9: =F9/F8-1 -> 0.0062156499 | I9: Market Beta | J9: 0.01 | R9: Beta | S9: =S30 -> 0.0052044999
B10: Dec 1, 2025 | C10: 3782.2 | D10: =C10/C9-1 -> 0.025125356 | F10: 14744 | G10: =F10/F9-1 -> -0.01909061 | I10: Market Beta Weight | J10: 0.25
B11: Nov 1, 2025 | C11: 3996.5 | D11: =C11/C10-1 -> 0.056660145 | F11: 14507.3 | G11: =F11/F10-1 -> -0.016053988
B12: Oct 1, 2025 | C12: 4153.5 | D12: =C12/C11-1 -> 0.039284374 | F12: 14826 | G12: =F12/F11-1 -> 0.02196825 | I12: Adjusted Beta | J12: =(J6*J7)+(J9*J10) -> 0.0064033749
B13: Sep 1, 2025 | C13: 4475.4 | D13: =C13/C12-1 -> 0.077500903 | F13: 14823.33 | G13: =F13/F12-1 -> -0.00018008903 | R13: SUMMARY OUTPUT
B14: Aug 1, 2025 | C14: 4756.6 | D14: =C14/C13-1 -> 0.062832373 | F14: 15489.33 | G14: =F14/F13-1 -> 0.044929176
B15: Jul 1, 2025 | C15: 4267.4 | D15: =C15/C14-1 -> -0.10284657 | F15: 14785.2 | G15: =F15/F14-1 -> -0.045459035 | R15: Regression Statistics
B16: Jun 1, 2025 | C16: 4372.3 | D16: =C16/C15-1 -> 0.024581713 | F16: 12584.3 | G16: =F16/F15-1 -> -0.14885832 | R16: Multiple R | S16: 0.017191231
B17: May 1, 2025 | C17: 4002.1 | D17: =C17/C16-1 -> -0.084669396 | F17: 11446.2 | G17: =F17/F16-1 -> -0.090438086 | R17: R Square | S17: 0.00029553844
B18: Apr 1, 2025 | C18: 4199.9 | D18: =C18/C17-1 -> 0.049424052 | F18: 12553.5 | G18: =F18/F17-1 -> 0.096739529 | R18: Adjusted R Square | S18: -0.045145573
B19: Mar 1, 2025 | C19: 4083.2 | D19: =C19/C18-1 -> -0.027786376 | F19: 11554.8 | G19: =F19/F18-1 -> -0.079555502 | R19: Standard Error | S19: 0.089838074
B20: Feb 1, 2025 | C20: 3403.95 | D20: =C20/C19-1 -> -0.16635237 | F20: 14856 | G20: =F20/F19-1 -> 0.28569945 | R20: Observations | S20: 24
B21: Jan 1, 2025 | C21: 3664.65 | D21: =C21/C20-1 -> 0.076587494 | F21: 14785.55 | G21: =F21/F20-1 -> -0.0047421917
B22: Dec 1, 2024 | C22: 3616.85 | D22: =C22/C21-1 -> -0.013043538 | F22: 14444.4 | G22: =F22/F21-1 -> -0.023073203 | R22: ANOVA
B23: Nov 1, 2024 | C23: 3709.6 | D23: =C23/C22-1 -> 0.025643861 | F23: 12222.2 | G23: =F23/F22-1 -> -0.15384509 | S23: df | T23: SS | U23: MS | V23: F | W23: Significance F
B24: Oct 1, 2024 | C24: 3930.7 | D24: =C24/C23-1 -> 0.059602113 | F24: 14445.2 | G24: =F24/F23-1 -> 0.18188215 | R24: Regression | S24: 1 | T24: 5.2491126e-05 | U24: 5.2491126e-05 | V24: 0.0065037677 | W24: 0.93645268
B25: Sep 1, 2024 | C25: 5096.3 | D25: =C25/C24-1 -> 0.29653751 | F25: 14523.2 | G25: =F25/F24-1 -> 0.0053997176 | R25: Residual | S25: 22 | T25: 0.17755935 | U25: 0.0080708795
B26: Aug 1, 2024 | C26: 4927.45 | D26: =C26/C25-1 -> -0.03313188 | F26: 25896.33 | G26: =F26/F25-1 -> 0.78310083 | R26: Total | S26: 23 | T26: 0.17761184
B27: Jul 1, 2024 | C27: 4935.95 | D27: =C27/C26-1 -> 0.0017250302 | F27: 47895.33 | G27: =F27/F26-1 -> 0.84950261
B28: Jun 1, 2024 | C28: 4716.75 | D28: =C28/C27-1 -> -0.044408878 | F28: 25897.55 | G28: =F28/F27-1 -> -0.45928862 | S28: Coefficients | T28: Standard Error | U28: t Stat | V28: P-value | W28: Lower 95% | X28: Upper 95% | Y28: Lower 95.0% | Z28: Upper 95.0%
B29: May 1, 2024 | C29: 4302.15 | D29: =C29/C28-1 -> -0.087899507 | F29: 13556.2 | G29: =F29/F28-1 -> -0.47654508 | R29: Intercept | S29: 0.010480432 | T29: 0.018502872 | U29: 0.56642189 | V29: 0.57684033 | W29: -0.027892176 | X29: 0.048853039 | Y29: -0.027892176 | Z29: 0.048853039
B30: Apr 1, 2024 | C30: 4603.8 | D30: =C30/C29-1 -> 0.070116105 | F30: 14222.2 | G30: =F30/F29-1 -> 0.049128812 | R30: X Variable 1 | S30: 0.0052044999 | T30: 0.064535175 | U30: 0.080645941 | V30: 0.93645268 | W30: -0.12863326 | X30: 0.13904226 | Y30: -0.12863326 | Z30: 0.13904226
B31: Mar 1, 2024 | C31: 4625.6 | D31: =C31/C30-1 -> 0.0047352187 | F31: 15368.9 | G31: =F31/F30-1 -> 0.08062747

Sheet COMPS BETA
B4: S.No. | C4: Name | D4: CMP Rs. | E4: Mar Cap Rs.Cr. | F4: Debt Rs.Cr. | G4: Debt / Eq
B5: 1 | C5: Avenue Super. | D5: 3875.8 | E5: 252211.12 | F5: 1609.19 | G5: 0.07
B6: 2 | C6: Eternal | D6: 232.57 | E6: 224438.21 | F6: 3351 | G6: 0.11
B7: 3 | C7: Trent | D7: 3722.8 | E7: 132340.87 | F7: 2348.57 | G7: 0.38
B8: 4 | C8: Lenskart Solut. | D8: 520.1 | E8: 90311 | F8: 2857.8 | G8: 0.45
B9: 5 | C9: Swiggy | D9: 301.5 | E9: 83223.45 | F9: 2491 | G9: 0.25

Sheet Rm 
B2: Return on Markets
B4: Year | C4: Annual
B5: 2000 | C5: -0.1465 | E5: Average Return | F5: =AVERAGE(C5:C29) -> 0.153348
B6: 2001 | C6: -0.1618 | E6: Dividend Yeild | F6: 1.28% 1
B7: 2002 | C7: 0.0325 | E7: Toatal Market Return | F7: =SUM(F5:F6) -> 0.153348
B8: 2003 | C8: 0.719
B9: 2004 | C9: 0.1068
B10: 2005 | C10: 0.3634
B11: 2006 | C11: 0.3983
B12: 2007 | C12: 0.5477
B13: 2008 | C13: -0.5179
B14: 2009 | C14: 0.7576
B15: 2010 | C15: 0.1795
B16: 2011 | C16: -0.2462
B17: 2012 | C17: 0.277
B18: 2013 | C18: 0.0676
B19: 2014 | C19: 0.3139
... B29: 2024 | C29: 0.0875
